Metadata-Version: 1.0
Name: distributions-mfp
Version: 0.1.2
Summary: Gaussian distributions
Home-page: UNKNOWN
Author: Wendy Navarrete
Author-email: UNKNOWN
License: UNKNOWN
Platform: UNKNOWN
